fudan_jwc_news/__init__.py
fudan_jwc_news/jwc_news.py
fudan_jwc_news-0.5.2.dist-info/LICENSE
fudan_jwc_news-0.5.2.dist-info/METADATA
fudan_jwc_news-0.5.2.dist-info/WHEEL
fudan_jwc_news-0.5.2.dist-info/entry_points.txt
fudan_jwc_news-0.5.2.dist-info/RECORD
