Metadata-Version: 2.1
Name: fudan-jwc-news
Version: 0.5.2
Summary: Read Fudan JWC news from your terminal
Home-page: https://github.com/tddschn/fudan-jwc-news
License: MIT
Keywords: fudan,news
Author: Xinyuan Chen
Author-email: 45612704+tddschn@users.noreply.github.com
Requires-Python: >=3.10,<4.0
Classifier: License :: OSI Approved :: MIT License
Classifier: Programming Language :: Python :: 3
Classifier: Programming Language :: Python :: 3.10
Classifier: Programming Language :: Python :: 3.11
Classifier: Topic :: Utilities
Requires-Dist: bs4 (>=0.0.1,<0.0.2)
Requires-Dist: pyinstrument (>=4.1.1,<5.0.0)
Requires-Dist: requests (>=2.27.1,<3.0.0)
Requires-Dist: typer (>=0.4.1,<0.5.0)
Project-URL: Bug Tracker, https://github.com/tddschn/fudan-jwc-news/issues
Project-URL: Repository, https://github.com/tddschn/fudan-jwc-news
